README.md
checkssl
checkssl.py
setup.py
CheckSSL/__init__.py
CheckSSL.egg-info/PKG-INFO
CheckSSL.egg-info/SOURCES.txt
CheckSSL.egg-info/dependency_links.txt
CheckSSL.egg-info/requires.txt
CheckSSL.egg-info/top_level.txt